{
  "characters": [
    {
      "name": "RamzaChapter1",
      "spriteNames": [
        "ramuza"
      ],
      "texFiles": [830, 831],
      "defaultTheme": "original",
      "availableThemes": [
        "original",
        "white_heretic",
        "dark_knight",
        "crimson_blade"
      ]
    },
    {
      "name": "RamzaChapter23",
      "spriteNames": [
        "ramuza2"
      ],
      "texFiles": [832, 833],
      "defaultTheme": "original",
      "availableThemes": [
        "original",
        "white_heretic",
        "dark_knight",
        "crimson_blade"
      ]
    },
    {
      "name": "RamzaChapter4",
      "spriteNames": [
        "ramuza3"
      ],
      "texFiles": [834, 835],
      "defaultTheme": "original",
      "availableThemes": [
        "original",
        "white_heretic",
        "dark_knight",
        "crimson_blade"
      ]
    },
    {
      "name": "Agrias",
      "spriteNames": [
        "aguri",
        "kanba"
      ],
      "texFiles": [880, 881, 914, 915],
      "defaultTheme": "original",
      "availableThemes": [
        "original",
        "gun_slinger",
        "crimson_assassin",
        "shadow_dancer",
        "royal_commander",
        "temple_commander",
        "grand_duke",
        "temple_engineer",
        "demon_hunter",
        "mysterious_knight",
        "mime_dancer",
        "diplomat_blade"
      ]
    },
    {
      "name": "Cloud",
      "spriteNames": [
        "cloud"
      ],
      "texFiles": [910, 911],
      "defaultTheme": "original",
      "availableThemes": [
        "original",
        "holy_soldier",
        "young_soldier",
        "sky_pirate",
        "academy_scholar",
        "merchant_blade",
        "valkyrie_soldier"
      ]
    },
    {
      "name": "Mustadio",
      "spriteNames": [
        "musu",
        "garu"
      ],
      "texFiles": [888, 889],
      "defaultTheme": "original",
      "availableThemes": [
        "original",
        "noble_engineer",
        "crimson_engineer",
        "shadow_machinist",
        "royal_gunner",
        "divine_artificer",
        "mourning_gun",
        "white_rose"
      ]
    },
    {
      "name": "Orlandeau",
      "spriteNames": [
        "oru"
      ],
      "texFiles": [854, 855],
      "defaultTheme": "original",
      "availableThemes": [
        "original",
        "thunder_god",
        "divine_thunder",
        "demon_god"
      ]
    },
    {
      "name": "Reis",
      "spriteNames": [
        "reze",
        "reze_d"
      ],
      "texFiles": [858, 859],
      "defaultTheme": "original",
      "availableThemes": [
        "original",
        "bronze_armor",
        "copper_shine",
        "coral",
        "crimson_red",
        "deep_purple",
        "desert_sand",
        "electric_blue",
        "forest_green",
        "golden_yellow",
        "iron_gray",
        "lavender",
        "lime_green",
        "magenta",
        "midnight_black",
        "mint_green",
        "moss_green",
        "ocean_blue",
        "orange_flame",
        "platinum",
        "rose_pink",
        "royal_blue",
        "silver_steel",
        "sunset_orange",
        "turquoise",
        "violet",
        "dragon_priestess"
      ]
    },
    {
      "name": "Rapha",
      "spriteNames": [
        "h79"
      ],
      "texFiles": [870, 871],
      "defaultTheme": "original",
      "availableThemes": [
        "original",
        "twilight_blend",
        "thunder_maiden",
        "fallen_oracle",
        "ancient_witch",
        "shadow_oracle"
      ]
    },
    {
      "name": "Marach",
      "spriteNames": [
        "mara"
      ],
      "texFiles": [872, 873],
      "defaultTheme": "original",
      "availableThemes": [
        "original",
        "nightmare_armor",
        "divine_herald",
        "storm_herald",
        "heaven_twin",
        "temple_artificer",
        "void_herald",
        "enigma_caster",
        "dragon_sage",
        "dragon_priestess",
        "scholar_prophet"
      ]
    },
    {
      "name": "Beowulf",
      "spriteNames": [
        "beio"
      ],
      "texFiles": [882, 883],
      "defaultTheme": "original",
      "availableThemes": [
        "original",
        "holy_templar",
        "machinist_knight",
        "twilight_templar",
        "shadow_knight",
        "noble_guardian",
        "divine_blade",
        "forge_templar",
        "demon_slayer",
        "vampire_lord",
        "ancient_guardian"
      ]
    },
    {
      "name": "Meliadoul",
      "spriteNames": [
        "h80"
      ],
      "texFiles": [905, 906],
      "defaultTheme": "original",
      "availableThemes": [
        "original",
        "holy_divine",
        "night_blade",
        "shadow_strike",
        "royal_crusader",
        "engineer_knight",
        "temple_divine",
        "elder_wisdom",
        "siege_engineer",
        "funeral_knight",
        "plague_knight",
        "dragon_general"
      ]
    }
  ]
}